{"imagelist":[{"x":-6,"y":"max","width":1.5,"height":0.5,"bitmapWidth":-300,"bitmapHeight":-100,"image":"img/cannon_1.png","shape":"polygon","type":"kinematic","name":"cannon","description":"Cannon 1","friction":0,"restitution":0,"centerX":0.6,"centerY":0,"angle":0},{"x":6,"y":"max","width":1.5,"height":0.5,"bitmapWidth":-300,"bitmapHeight":-100,"image":"img/cannon_2.png","shape":"polygon","type":"kinematic","name":"cannon","description":"Cannon 2","friction":0,"restitution":0,"centerX":0.6,"centerY":0,"angle":0},{"x":-1.3962524722795937,"y":2.4723873801040464,"width":1.2,"height":0.3,"bitmapWidth":-300,"bitmapHeight":-100,"image":"img/blocker.png","shape":"polygon","type":"static","name":"blocker","description":"Platform 1","friction":1,"restitution":0,"centerX":0,"centerY":0,"angle":0},{"x":-1.3962524722795937,"y":1.5723873801040464,"width":0.6,"height":0.6,"bitmapWidth":-89,"bitmapHeight":-97,"image":"img/tower/tower_2.png","shape":"polygon","type":"static","name":"building1","description":"Target 1","friction":1,"restitution":0,"centerX":0,"centerY":0,"angle":0},{"x":2.007136591970921,"y":-0.815995403206907,"width":1.2,"height":0.3,"bitmapWidth":-300,"bitmapHeight":-100,"image":"img/blocker.png","shape":"polygon","type":"static","name":"blocker","description":"Platform 1","friction":1,"restitution":0,"centerX":0,"centerY":0,"angle":0},{"x":2.007136591970921,"y":-1.715995403206907,"width":0.6,"height":0.6,"bitmapWidth":-89,"bitmapHeight":-97,"image":"img/tower/tower_2.png","shape":"polygon","type":"static","name":"building1","description":"Target 1","friction":1,"restitution":0,"centerX":0,"centerY":0,"angle":0},{"x":-5.056012997883372,"y":-2.9199206112721003,"width":1.289311151043512,"height":0.31438879324123264,"bitmapWidth":-300,"bitmapHeight":-100,"image":"img/blocker.png","shape":"polygon","type":"static","name":"blocker","description":"Platform 1","friction":1,"restitution":0,"centerX":0,"centerY":0,"angle":1.5707963267948966},{"x":-3.583708597798832,"y":1.0840544925886206,"width":0.6182795247528702,"height":0.43757196911610663,"bitmapWidth":-300,"bitmapHeight":-100,"image":"img/blocker.png","shape":"polygon","type":"static","name":"blocker","description":"Platform 1","friction":1,"restitution":0,"centerX":0,"centerY":0,"angle":0},{"x":6.0258159529836846,"y":-2.4002092466293834,"width":1.523532973160036,"height":0.35979300355538724,"bitmapWidth":-300,"bitmapHeight":-100,"image":"img/blocker.png","shape":"polygon","type":"static","name":"blocker","description":"Platform 1","friction":1,"restitution":0,"centerX":0,"centerY":0,"angle":1.5707963267948966},{"x":-3.6577020799182356,"y":-0.03140399083960821,"width":0.693450836604461,"height":0.3594046871177852,"bitmapWidth":-300,"bitmapHeight":-100,"image":"img/blocker.png","shape":"polygon","type":"static","name":"blocker","description":"Platform 1","friction":1,"restitution":0,"centerX":0,"centerY":0,"angle":1.5707963267948966}]} 