{"imagelist":[{"x":-6,"y":"max","width":1.5,"height":0.5,"bitmapWidth":-300,"bitmapHeight":-100,"image":"img/cannon_1.png","shape":"polygon","type":"kinematic","name":"cannon","description":"Cannon 1","friction":0,"restitution":0,"centerX":0.6,"centerY":0,"angle":0},{"x":6,"y":"max","width":1.5,"height":0.5,"bitmapWidth":-300,"bitmapHeight":-100,"image":"img/cannon_2.png","shape":"polygon","type":"kinematic","name":"cannon","description":"Cannon 2","friction":0,"restitution":0,"centerX":0.6,"centerY":0,"angle":0},{"x":1.9475784430559724,"y":1.8757015430368487,"width":1.2,"height":0.3,"bitmapWidth":-300,"bitmapHeight":-100,"image":"img/blocker.png","shape":"polygon","type":"static","name":"blocker","description":"Platform 1","friction":1,"restitution":0,"centerX":0,"centerY":0,"angle":0},{"x":1.9475784430559724,"y":0.9757015430368486,"width":0.6,"height":0.6,"bitmapWidth":-89,"bitmapHeight":-97,"image":"img/tower/tower_2.png","shape":"polygon","type":"static","name":"building1","description":"Target 1","friction":1,"restitution":0,"centerX":0,"centerY":0,"angle":0},{"x":-3.3920329602062704,"y":3.0640135007211935,"width":1.2,"height":0.3,"bitmapWidth":-300,"bitmapHeight":-100,"image":"img/blocker.png","shape":"polygon","type":"static","name":"blocker","description":"Platform 1","friction":1,"restitution":0,"centerX":0,"centerY":0,"angle":0},{"x":-3.3920329602062704,"y":2.1640135007211936,"width":0.6,"height":0.6,"bitmapWidth":-89,"bitmapHeight":-97,"image":"img/tower/tower_2.png","shape":"polygon","type":"static","name":"building1","description":"Target 1","friction":1,"restitution":0,"centerX":0,"centerY":0,"angle":0},{"x":4.52397887554951,"y":-0.9413247316004707,"width":1.2,"height":0.3,"bitmapWidth":-300,"bitmapHeight":-100,"image":"img/blocker.png","shape":"polygon","type":"static","name":"blocker","description":"Platform 1","friction":1,"restitution":0,"centerX":0,"centerY":0,"angle":0},{"x":4.52397887554951,"y":-1.8413247316004706,"width":0.6,"height":0.6,"bitmapWidth":-89,"bitmapHeight":-97,"image":"img/tower/tower_2.png","shape":"polygon","type":"static","name":"building1","description":"Target 1","friction":1,"restitution":0,"centerX":0,"centerY":0,"angle":0},{"x":-5.834679477629252,"y":0.4527993454528043,"width":1.0385936554754154,"height":0.49634284088388086,"bitmapWidth":-300,"bitmapHeight":-100,"image":"img/blocker.png","shape":"polygon","type":"static","name":"blocker","description":"Platform 1","friction":1,"restitution":0,"centerX":0,"centerY":0,"angle":-1.0471975511965976},{"x":-6.760263041276485,"y":-2.360862814399879,"width":0.8446013647131622,"height":0.4097449252847582,"bitmapWidth":-300,"bitmapHeight":-100,"image":"img/blocker.png","shape":"polygon","type":"static","name":"blocker","description":"Platform 1","friction":1,"restitution":0,"centerX":0,"centerY":0,"angle":-1.0471975511965976},{"x":6.763044476988725,"y":-0.14549264149274688,"width":1.0225269266171382,"height":0.34428435950540004,"bitmapWidth":-300,"bitmapHeight":-100,"image":"img/blocker.png","shape":"polygon","type":"static","name":"blocker","description":"Platform 1","friction":1,"restitution":0,"centerX":0,"centerY":0,"angle":0.5235987755982988},{"x":-1.230772296148352,"y":-2.6702590028173288,"width":0.8164792305557057,"height":0.32792566288262603,"bitmapWidth":-300,"bitmapHeight":-100,"image":"img/blocker.png","shape":"polygon","type":"static","name":"blocker","description":"Platform 1","friction":1,"restitution":0,"centerX":0,"centerY":0,"angle":1.0471975511965976},{"x":-1.0053719894774256,"y":0.49219034488312907,"width":0.899001264036633,"height":0.38734895740635694,"bitmapWidth":-300,"bitmapHeight":-100,"image":"img/blocker.png","shape":"polygon","type":"static","name":"blocker","description":"Platform 1","friction":1,"restitution":0,"centerX":0,"centerY":0,"angle":1.5707963267948966},{"x":-6.796416184245609,"y":-3.1306224572565404,"width":1.36557025895454,"height":0.32077578897587955,"bitmapWidth":-300,"bitmapHeight":-100,"image":"img/blocker.png","shape":"polygon","type":"static","name":"blocker","description":"Platform 1","friction":1,"restitution":0,"centerX":0,"centerY":0,"angle":0.5235987755982988},{"x":6.745543027687818,"y":-3.148538147115614,"width":0.6612835823558271,"height":0.3828678345773369,"bitmapWidth":-300,"bitmapHeight":-100,"image":"img/blocker.png","shape":"polygon","type":"static","name":"blocker","description":"Platform 1","friction":1,"restitution":0,"centerX":0,"centerY":0,"angle":1.5707963267948966}]}